dbtos3/__init__.py
dbtos3/exchangeratesapi_model/__init__.py
dbtos3/exchangeratesapi_model/api.py
dbtos3/mysql_model/__init__.py
dbtos3/mysql_model/db.py
dbtos3/postgres_model/__init__.py
dbtos3/postgres_model/db.py
dbtos3/s3_model/__init__.py
dbtos3/s3_model/service.py
dbtos3/sentry_model/__init__.py
dbtos3/sentry_model/api.py
dbtos3/sqlite_model/__init__.py
dbtos3/sqlite_model/catalogue.py
dbtos3-0.0.5.dist-info/LICENSE
dbtos3-0.0.5.dist-info/METADATA
dbtos3-0.0.5.dist-info/WHEEL
dbtos3-0.0.5.dist-info/top_level.txt
dbtos3-0.0.5.dist-info/RECORD
