Metadata-Version: 2.1
Name: dbtos3
Version: 0.0.5
Summary: Replication & Full Load Application for multiple databases to s3
Home-page: https://github.com/DirksCGM/DBtoS3
Author: DirkSCGM
Author-email: dirkscgm@gmail.com
License: UNKNOWN
Project-URL: Documentation, https://github.com/DirksCGM/DBtoS3/wiki
Project-URL: Foundation, https://perceptechdata.com/perceptech-data-software-foundation/
Project-URL: Source, https://github.com/DirksCGM/DBtoS3
Keywords: postgresql,s3,aws,mysql,sentry,replication,sql
Platform: UNKNOWN
Classifier: Programming Language :: Python :: 3 :: Only
Requires-Python: >=3
Requires-Dist: boto3
Requires-Dist: numpy
Requires-Dist: psycopg2
Requires-Dist: pandas
Requires-Dist: mysql-connector-python
Requires-Dist: flask
